{
  "$schema": "https://developer.microsoft.com/json-schemas/fabric/item/report/definition/bookmark/1.4.0/schema.json",
  "displayName": "Purchases by Item Link",
  "name": "Bookmarkf7278fa55d14e9c26de4",
  "options": {
    "targetVisualNames": [],
    "suppressData": true
  },
  "explorationState": {
    "version": "1.3",
    "activeSection": "ReportSection2762d22665a83d3665a4",
    "sections": {
      "ReportSection2762d22665a83d3665a4": {
        "visualContainers": {}
      }
    },
    "objects": {
      "merge": {
        "outspacePane": [
          {
            "properties": {
              "expanded": {
                "expr": {
                  "Literal": {
                    "Value": "false"
                  }
                }
              }
            }
          }
        ]
      }
    }
  }
}