{
  "$schema": "https://developer.microsoft.com/json-schemas/fabric/item/report/definition/page/2.0.0/schema.json",
  "name": "1782621aa0d0e087ed20",
  "displayName": "Journey to Net-Zero Carbon",
  "displayOption": "FitToPage",
  "height": 720,
  "width": 1280,
  "filterConfig": {
    "filters": [
      {
        "name": "81885c3090639ac3c687",
        "field": {
          "Column": {
            "Expression": {
              "SourceRef": {
                "Entity": "Country/Region"
              }
            },
            "Property": "Country Region Code"
          }
        },
        "type": "Categorical",
        "howCreated": "User"
      },
      {
        "name": "4975141f33d805247822",
        "field": {
          "Column": {
            "Expression": {
              "SourceRef": {
                "Entity": "Country/Region"
              }
            },
            "Property": "Country Region Name"
          }
        },
        "type": "Categorical",
        "howCreated": "User"
      },
      {
        "name": "7ad00d8e531d644195c0",
        "field": {
          "HierarchyLevel": {
            "Expression": {
              "Hierarchy": {
                "Expression": {
                  "SourceRef": {
                    "Entity": "Date"
                  }
                },
                "Hierarchy": "Fiscal Year-Month"
              }
            },
            "Level": "Fiscal Month Year"
          }
        },
        "type": "Categorical",
        "howCreated": "User"
      },
      {
        "name": "5b33ef0653529e460591",
        "field": {
          "HierarchyLevel": {
            "Expression": {
              "Hierarchy": {
                "Expression": {
                  "SourceRef": {
                    "Entity": "Date"
                  }
                },
                "Hierarchy": "Fiscal Year-Month"
              }
            },
            "Level": "Fiscal Year"
          }
        },
        "type": "Categorical",
        "howCreated": "User"
      },
      {
        "name": "22259b0448b013da84a0",
        "field": {
          "Column": {
            "Expression": {
              "SourceRef": {
                "Entity": "Sustainability Goals"
              }
            },
            "Property": "Main Goal"
          }
        },
        "type": "Categorical",
        "howCreated": "User"
      },
      {
        "name": "0a0beccf60c0bab3888a",
        "field": {
          "Column": {
            "Expression": {
              "SourceRef": {
                "Entity": "Sustainability Goals"
              }
            },
            "Property": "Name"
          }
        },
        "type": "Categorical",
        "howCreated": "User"
      },
      {
        "name": "9af7272fd98a94263879",
        "field": {
          "Column": {
            "Expression": {
              "SourceRef": {
                "Entity": "Sustainability Goals"
              }
            },
            "Property": "No."
          }
        },
        "type": "Categorical",
        "howCreated": "User"
      },
      {
        "name": "51a47afcdcdc3831503b",
        "field": {
          "Column": {
            "Expression": {
              "SourceRef": {
                "Entity": "Sustainability Goals"
              }
            },
            "Property": "Owner"
          }
        },
        "type": "Categorical",
        "howCreated": "User"
      },
      {
        "name": "8472868bd1079069a9dd",
        "field": {
          "Column": {
            "Expression": {
              "SourceRef": {
                "Entity": "Sustainability Sub-Account Categories"
              }
            },
            "Property": "Renewable Energy"
          }
        },
        "type": "Categorical",
        "howCreated": "User"
      },
      {
        "name": "06beda41035c9beb019b",
        "field": {
          "Column": {
            "Expression": {
              "SourceRef": {
                "Entity": "Sustainability Goals"
              }
            },
            "Property": "Score Card No."
          }
        },
        "type": "Categorical",
        "howCreated": "User"
      },
      {
        "name": "ab6793ca32c765d02081",
        "field": {
          "Column": {
            "Expression": {
              "SourceRef": {
                "Entity": "Sustainability Goals"
              }
            },
            "Property": "Start Date"
          }
        },
        "type": "Categorical",
        "howCreated": "User"
      },
      {
        "name": "9b14036ed464d3945066",
        "field": {
          "Column": {
            "Expression": {
              "SourceRef": {
                "Entity": "Sustainability Sub-Account Categories"
              }
            },
            "Property": "Sub-Category Code"
          }
        },
        "type": "Categorical",
        "howCreated": "User"
      },
      {
        "name": "9c2011ae19be094d03b9",
        "field": {
          "Column": {
            "Expression": {
              "SourceRef": {
                "Entity": "Sustainability Sub-Account Categories"
              }
            },
            "Property": "Sub-Category Description"
          }
        },
        "type": "Categorical",
        "howCreated": "User"
      },
      {
        "name": "6ecb119e0db49c4de580",
        "field": {
          "Column": {
            "Expression": {
              "SourceRef": {
                "Entity": "Sustainability Accounts"
              }
            },
            "Property": "Sustainability Account Category"
          }
        },
        "type": "Categorical",
        "howCreated": "User"
      },
      {
        "name": "5b28f01f12bec8b0536a",
        "field": {
          "Column": {
            "Expression": {
              "SourceRef": {
                "Entity": "Sustainability Account Category"
              }
            },
            "Property": "Sustainability Account Category Code"
          }
        },
        "type": "Categorical",
        "howCreated": "User"
      },
      {
        "name": "23c56e2add2b2b1010b6",
        "field": {
          "Column": {
            "Expression": {
              "SourceRef": {
                "Entity": "Sustainability Account Category"
              }
            },
            "Property": "Sustainability Account Category Description"
          }
        },
        "type": "Categorical",
        "howCreated": "User"
      },
      {
        "name": "4486c92793982b605993",
        "field": {
          "Column": {
            "Expression": {
              "SourceRef": {
                "Entity": "Sustainability Accounts"
              }
            },
            "Property": "Sustainability Account Name"
          }
        },
        "type": "Categorical",
        "howCreated": "User"
      },
      {
        "name": "32d071dee091ada99308",
        "field": {
          "Column": {
            "Expression": {
              "SourceRef": {
                "Entity": "Sustainability Accounts"
              }
            },
            "Property": "Sustainability Account No."
          }
        },
        "type": "Categorical",
        "howCreated": "User"
      },
      {
        "name": "98f92fb76333554732ed",
        "field": {
          "Column": {
            "Expression": {
              "SourceRef": {
                "Entity": "Responsibility Centre"
              }
            },
            "Property": "Responsibility Centre Code"
          }
        },
        "type": "Categorical",
        "howCreated": "User"
      },
      {
        "name": "b782e52381c9c593dc91",
        "field": {
          "Column": {
            "Expression": {
              "SourceRef": {
                "Entity": "Responsibility Centre"
              }
            },
            "Property": "Responsibility Centre Name"
          }
        },
        "type": "Categorical",
        "howCreated": "User"
      }
    ],
    "filterSortOrder": "Ascending"
  }
}