{
  "$schema": "https://developer.microsoft.com/json-schemas/fabric/item/report/definition/visualContainer/2.4.0/schema.json",
  "name": "94b55dca0ba01b732873",
  "position": {
    "x": 338.13248204309656,
    "y": 69.465283320031929,
    "z": 7000,
    "height": 229.84836392657621,
    "width": 295.22745411013568,
    "tabOrder": 7000
  },
  "visual": {
    "visualType": "donutChart",
    "query": {
      "queryState": {
        "Category": {
          "projections": [
            {
              "field": {
                "Column": {
                  "Expression": {
                    "SourceRef": {
                      "Entity": "Item Category"
                    }
                  },
                  "Property": "Item Category Code"
                }
              },
              "queryRef": "Item Category.Item Category Code",
              "nativeQueryRef": "Item Category Code",
              "active": true
            }
          ]
        },
        "Tooltips": {
          "projections": [
            {
              "field": {
                "Measure": {
                  "Expression": {
                    "SourceRef": {
                      "Entity": "Sales Budget"
                    }
                  },
                  "Property": "Budget Amount"
                }
              },
              "queryRef": "Sales Budget.Budget Amount",
              "nativeQueryRef": "Budget Amount"
            },
            {
              "field": {
                "Measure": {
                  "Expression": {
                    "SourceRef": {
                      "Entity": "Sales Budget"
                    }
                  },
                  "Property": "Budget Amount Variance"
                }
              },
              "queryRef": "Sales Budget.Budget Amount Variance",
              "nativeQueryRef": "Budget Amount Variance"
            },
            {
              "field": {
                "Measure": {
                  "Expression": {
                    "SourceRef": {
                      "Entity": "Sales Budget"
                    }
                  },
                  "Property": "Budget Amount Variance %"
                }
              },
              "queryRef": "Sales Budget.Budget Amount Variance %",
              "nativeQueryRef": "Budget Amount Variance %"
            }
          ]
        },
        "Y": {
          "projections": [
            {
              "field": {
                "Measure": {
                  "Expression": {
                    "SourceRef": {
                      "Entity": "Documents"
                    }
                  },
                  "Property": "Sales (LCY)"
                }
              },
              "queryRef": "Divide(Documents.Sales (LCY), ScopedEval(Documents.Sales (LCY), []))",
              "nativeQueryRef": "Sales (LCY)"
            }
          ]
        }
      },
      "sortDefinition": {
        "sort": [
          {
            "field": {
              "Measure": {
                "Expression": {
                  "SourceRef": {
                    "Entity": "Documents"
                  }
                },
                "Property": "Sales (LCY)"
              }
            },
            "direction": "Descending"
          }
        ],
        "isDefaultSort": true
      }
    },
    "objects": {
      "labels": [
        {
          "properties": {
            "labelStyle": {
              "expr": {
                "Literal": {
                  "Value": "'Category, percent of total'"
                }
              }
            }
          }
        }
      ]
    },
    "visualContainerObjects": {
      "background": [
        {
          "properties": {
            "show": {
              "expr": {
                "Literal": {
                  "Value": "true"
                }
              }
            },
            "transparency": {
              "expr": {
                "Literal": {
                  "Value": "0D"
                }
              }
            }
          }
        }
      ],
      "title": [
        {
          "properties": {
            "text": {
              "expr": {
                "Measure": {
                  "Expression": {
                    "SourceRef": {
                      "Entity": "Translated Localized Labels"
                    }
                  },
                  "Property": "Sales % by Category Label"
                }
              }
            },
            "show": {
              "expr": {
                "Literal": {
                  "Value": "true"
                }
              }
            }
          }
        }
      ],
      "visualHeader": [
        {
          "properties": {
            "show": {
              "expr": {
                "Literal": {
                  "Value": "true"
                }
              }
            }
          }
        }
      ],
      "padding": [
        {
          "properties": {
            "left": {
              "expr": {
                "Literal": {
                  "Value": "20D"
                }
              }
            }
          }
        }
      ]
    }
  },
  "filterConfig": {
    "filters": [
      {
        "name": "a24af62e5b09d055215b",
        "field": {
          "Arithmetic": {
            "Left": {
              "Measure": {
                "Expression": {
                  "SourceRef": {
                    "Entity": "Documents"
                  }
                },
                "Property": "Sales (LCY)"
              }
            },
            "Right": {
              "ScopedEval": {
                "Expression": {
                  "Measure": {
                    "Expression": {
                      "SourceRef": {
                        "Entity": "Documents"
                      }
                    },
                    "Property": "Sales (LCY)"
                  }
                },
                "Scope": []
              }
            },
            "Operator": 3
          }
        },
        "type": "Advanced",
        "howCreated": "User"
      }
    ]
  }
}