{
  "$schema": "https://developer.microsoft.com/json-schemas/fabric/item/report/definition/visualContainer/2.4.0/schema.json",
  "name": "64a61c0e6aa5314f449e",
  "position": {
    "x": 26.522522522522522,
    "y": 324.036036036036,
    "z": 0,
    "height": 370.16216216216219,
    "width": 1226.9549549549549,
    "tabOrder": 0
  },
  "visual": {
    "visualType": "pivotTable",
    "query": {
      "queryState": {
        "Rows": {
          "projections": [
            {
              "field": {
                "Column": {
                  "Expression": {
                    "SourceRef": {
                      "Entity": "Production Orders"
                    }
                  },
                  "Property": "Production Order"
                }
              },
              "queryRef": "Production Orders.Production Order",
              "nativeQueryRef": "Production Order",
              "active": true
            }
          ]
        },
        "Values": {
          "projections": [
            {
              "field": {
                "Measure": {
                  "Expression": {
                    "SourceRef": {
                      "Entity": "Production Orders"
                    }
                  },
                  "Property": "Planned Quantity"
                }
              },
              "queryRef": "Production Orders.Expected Quantity",
              "nativeQueryRef": "Expected Quantity"
            },
            {
              "field": {
                "Measure": {
                  "Expression": {
                    "SourceRef": {
                      "Entity": "Production Orders"
                    }
                  },
                  "Property": "Finished Quantity"
                }
              },
              "queryRef": "Production Orders.Finished Quantity",
              "nativeQueryRef": "Finished Quantity"
            },
            {
              "field": {
                "Measure": {
                  "Expression": {
                    "SourceRef": {
                      "Entity": "Production Orders"
                    }
                  },
                  "Property": "Variance Quantity"
                }
              },
              "queryRef": "Production Orders.Variance Quantity",
              "nativeQueryRef": "Variance Quantity"
            },
            {
              "field": {
                "Measure": {
                  "Expression": {
                    "SourceRef": {
                      "Entity": "Production Orders"
                    }
                  },
                  "Property": "Actual Material Cost"
                }
              },
              "queryRef": "Production Orders.Actual Material Cost",
              "nativeQueryRef": "Actual Material Cost"
            },
            {
              "field": {
                "Measure": {
                  "Expression": {
                    "SourceRef": {
                      "Entity": "Production Orders"
                    }
                  },
                  "Property": "Actual Capacity Cost"
                }
              },
              "queryRef": "Production Orders.Actual Capacity Cost",
              "nativeQueryRef": "Actual Capacity Cost"
            },
            {
              "field": {
                "Measure": {
                  "Expression": {
                    "SourceRef": {
                      "Entity": "Production Orders"
                    }
                  },
                  "Property": "Actual Capacity Overhead Cost"
                }
              },
              "queryRef": "Production Orders.Actual Capacity Overhead Cost",
              "nativeQueryRef": "Actual Capacity Overhead Cost"
            },
            {
              "field": {
                "Measure": {
                  "Expression": {
                    "SourceRef": {
                      "Entity": "Production Orders"
                    }
                  },
                  "Property": "Actual Manufacturing Overhead Cost"
                }
              },
              "queryRef": "Production Orders.Actual Manufacturing Overhead Cost",
              "nativeQueryRef": "Actual Manufacturing Overhead Cost"
            },
            {
              "field": {
                "Measure": {
                  "Expression": {
                    "SourceRef": {
                      "Entity": "Production Orders"
                    }
                  },
                  "Property": "Actual Subcontracted Cost"
                }
              },
              "queryRef": "Production Orders.Actual Subcontracted Cost",
              "nativeQueryRef": "Actual Subcontracted Cost"
            },
            {
              "field": {
                "Measure": {
                  "Expression": {
                    "SourceRef": {
                      "Entity": "Production Orders"
                    }
                  },
                  "Property": "Total Actual Cost"
                }
              },
              "queryRef": "Production Orders.Total Actual Cost",
              "nativeQueryRef": "Total Actual Cost"
            }
          ]
        }
      }
    },
    "expansionStates": [
      {
        "roles": [
          "Rows"
        ],
        "levels": [
          {
            "queryRefs": [
              "Production Orders.Production Order"
            ],
            "isCollapsed": true,
            "isPinned": true
          }
        ],
        "root": {}
      }
    ],
    "objects": {
      "columnWidth": [
        {
          "properties": {
            "value": {
              "expr": {
                "Literal": {
                  "Value": "113D"
                }
              }
            }
          },
          "selector": {
            "metadata": "Sales Measures.Average Sales Amount per Month"
          }
        },
        {
          "properties": {
            "value": {
              "expr": {
                "Literal": {
                  "Value": "95D"
                }
              }
            }
          },
          "selector": {
            "metadata": "Sales Measures.Average Sales Amount per Day"
          }
        },
        {
          "properties": {
            "value": {
              "expr": {
                "Literal": {
                  "Value": "125.9090909090909D"
                }
              }
            }
          },
          "selector": {
            "metadata": "Purchases.Purchase Amount"
          }
        },
        {
          "properties": {
            "value": {
              "expr": {
                "Literal": {
                  "Value": "83.46976744186045D"
                }
              }
            }
          },
          "selector": {
            "metadata": "Production Orders.Actual Material Cost"
          }
        },
        {
          "properties": {
            "value": {
              "expr": {
                "Literal": {
                  "Value": "83.27906976744185D"
                }
              }
            }
          },
          "selector": {
            "metadata": "Production Orders.Actual Capacity Cost"
          }
        },
        {
          "properties": {
            "value": {
              "expr": {
                "Literal": {
                  "Value": "94.22325581395349D"
                }
              }
            }
          },
          "selector": {
            "metadata": "Production Orders.Actual Capacity Overhead Cost"
          }
        },
        {
          "properties": {
            "value": {
              "expr": {
                "Literal": {
                  "Value": "130.7953488372093D"
                }
              }
            }
          },
          "selector": {
            "metadata": "Production Orders.Actual Manufacturing Overhead Cost"
          }
        }
      ]
    },
    "visualContainerObjects": {
      "title": [
        {
          "properties": {
            "text": {
              "expr": {
                "Measure": {
                  "Expression": {
                    "SourceRef": {
                      "Entity": "Translated Localized Labels"
                    }
                  },
                  "Property": "Finished Production Order Breakdown Label"
                }
              }
            }
          }
        }
      ],
      "background": [
        {
          "properties": {
            "show": {
              "expr": {
                "Literal": {
                  "Value": "true"
                }
              }
            },
            "transparency": {
              "expr": {
                "Literal": {
                  "Value": "0D"
                }
              }
            }
          }
        }
      ]
    }
  },
  "filterConfig": {
    "filters": [
      {
        "name": "8f302779fea04973c3da",
        "field": {
          "Arithmetic": {
            "Left": {
              "Measure": {
                "Expression": {
                  "SourceRef": {
                    "Entity": "Production Orders"
                  }
                },
                "Property": "Actual Capacity Cost"
              }
            },
            "Right": {
              "ScopedEval": {
                "Expression": {
                  "Measure": {
                    "Expression": {
                      "SourceRef": {
                        "Entity": "Production Orders"
                      }
                    },
                    "Property": "Actual Capacity Cost"
                  }
                },
                "Scope": [
                  {
                    "RoleRef": {
                      "Role": "Columns"
                    }
                  }
                ]
              }
            },
            "Operator": 3
          }
        },
        "type": "Advanced",
        "howCreated": "User"
      }
    ]
  }
}