{
  "$schema": "https://developer.microsoft.com/json-schemas/fabric/item/report/definition/page/2.0.0/schema.json",
  "name": "ReportSection05f91a4884be2b5c94ed",
  "displayName": "Actual vs. Budget",
  "displayOption": "FitToPage",
  "height": 720,
  "width": 1280,
  "filterConfig": {
    "filters": [
      {
        "name": "c485daae70722598a0d3",
        "ordinal": 0,
        "field": {
          "Column": {
            "Expression": {
              "SourceRef": {
                "Entity": "Sales Budget"
              }
            },
            "Property": "Budget Name"
          }
        },
        "type": "Categorical",
        "howCreated": "User"
      },
      {
        "name": "71d2fde8cae9c78b1b09",
        "ordinal": 1,
        "field": {
          "Column": {
            "Expression": {
              "SourceRef": {
                "Entity": "Customer"
              }
            },
            "Property": "Customer Name"
          }
        },
        "type": "Categorical",
        "howCreated": "User"
      },
      {
        "name": "f7d5b72e0b28b562a50e",
        "ordinal": 2,
        "field": {
          "Column": {
            "Expression": {
              "SourceRef": {
                "Entity": "Customer"
              }
            },
            "Property": "Customer No."
          }
        },
        "type": "Categorical",
        "howCreated": "User"
      },
      {
        "name": "5169de97361ef09d577c",
        "ordinal": 3,
        "field": {
          "Column": {
            "Expression": {
              "SourceRef": {
                "Entity": "Customer"
              }
            },
            "Property": "Customer No. & Name"
          }
        },
        "type": "Categorical",
        "howCreated": "User"
      },
      {
        "name": "f513cfea5be594d07890",
        "ordinal": 4,
        "field": {
          "Column": {
            "Expression": {
              "SourceRef": {
                "Entity": "Customer"
              }
            },
            "Property": "Customer Posting Group"
          }
        },
        "type": "Categorical",
        "howCreated": "User"
      },
      {
        "name": "Filtera1090bf7564a05095761",
        "ordinal": 5,
        "field": {
          "Column": {
            "Expression": {
              "SourceRef": {
                "Entity": "Date"
              }
            },
            "Property": "Date"
          }
        },
        "type": "Categorical",
        "howCreated": "User"
      },
      {
        "name": "94b16e5076c577d919b8",
        "ordinal": 6,
        "field": {
          "Column": {
            "Expression": {
              "SourceRef": {
                "Entity": "Documents"
              }
            },
            "Property": "Document Type"
          }
        },
        "type": "Categorical",
        "filter": {
          "Version": 2,
          "From": [
            {
              "Name": "s",
              "Entity": "Documents",
              "Type": 0
            }
          ],
          "Where": [
            {
              "Condition": {
                "Not": {
                  "Expression": {
                    "In": {
                      "Expressions": [
                        {
                          "Column": {
                            "Expression": {
                              "SourceRef": {
                                "Source": "s"
                              }
                            },
                            "Property": "Document Type"
                          }
                        }
                      ],
                      "Values": [
                        [
                          {
                            "Literal": {
                              "Value": "'Quote'"
                            }
                          }
                        ]
                      ]
                    }
                  }
                }
              }
            }
          ]
        },
        "howCreated": "User",
        "isHiddenInViewMode": true,
        "isLockedInViewMode": true,
        "objects": {
          "general": [
            {
              "properties": {
                "isInvertedSelectionMode": {
                  "expr": {
                    "Literal": {
                      "Value": "true"
                    }
                  }
                }
              }
            }
          ]
        }
      },
      {
        "name": "Filter16c2f8880d38a821ce3c",
        "ordinal": 7,
        "field": {
          "HierarchyLevel": {
            "Expression": {
              "Hierarchy": {
                "Expression": {
                  "SourceRef": {
                    "Entity": "Date"
                  }
                },
                "Hierarchy": "Fiscal Year-Quarter-Month-Week"
              }
            },
            "Level": "Fiscal Month Year"
          }
        },
        "type": "Categorical",
        "howCreated": "User"
      },
      {
        "name": "Filter8686e42ba63c17cb7088",
        "ordinal": 8,
        "field": {
          "HierarchyLevel": {
            "Expression": {
              "Hierarchy": {
                "Expression": {
                  "SourceRef": {
                    "Entity": "Date"
                  }
                },
                "Hierarchy": "Fiscal Year-Quarter-Month-Week"
              }
            },
            "Level": "Fiscal Quarter Year"
          }
        },
        "type": "Categorical",
        "howCreated": "User"
      },
      {
        "name": "Filtered981ea02d985b13ca70",
        "ordinal": 9,
        "field": {
          "HierarchyLevel": {
            "Expression": {
              "Hierarchy": {
                "Expression": {
                  "SourceRef": {
                    "Entity": "Date"
                  }
                },
                "Hierarchy": "Fiscal Year-Quarter-Month-Week"
              }
            },
            "Level": "Fiscal Week Year"
          }
        },
        "type": "Categorical",
        "howCreated": "User"
      },
      {
        "name": "Filter772ce8c7249d52c05645",
        "ordinal": 10,
        "field": {
          "HierarchyLevel": {
            "Expression": {
              "Hierarchy": {
                "Expression": {
                  "SourceRef": {
                    "Entity": "Date"
                  }
                },
                "Hierarchy": "Fiscal Year-Quarter-Month-Week"
              }
            },
            "Level": "Fiscal Year"
          }
        },
        "type": "Categorical",
        "howCreated": "User"
      },
      {
        "name": "1020742240c03fc6081e",
        "ordinal": 11,
        "field": {
          "Column": {
            "Expression": {
              "SourceRef": {
                "Entity": "Dimension Sets"
              }
            },
            "Property": "Global Dimension 1"
          }
        },
        "type": "Categorical",
        "howCreated": "User"
      },
      {
        "name": "8b56e70438523d7affdf",
        "ordinal": 12,
        "field": {
          "Column": {
            "Expression": {
              "SourceRef": {
                "Entity": "Dimension Sets"
              }
            },
            "Property": "Global Dimension 2"
          }
        },
        "type": "Categorical",
        "howCreated": "User"
      },
      {
        "name": "8278a0c451b0f57f04c0",
        "ordinal": 13,
        "field": {
          "Column": {
            "Expression": {
              "SourceRef": {
                "Entity": "Item"
              }
            },
            "Property": "Item Category Code"
          }
        },
        "type": "Categorical",
        "howCreated": "User"
      },
      {
        "name": "d6dd5addd5d28477d2d9",
        "ordinal": 14,
        "field": {
          "Column": {
            "Expression": {
              "SourceRef": {
                "Entity": "Item"
              }
            },
            "Property": "Item Category Description"
          }
        },
        "type": "Categorical",
        "howCreated": "User"
      },
      {
        "name": "d673b18ad50c59e8ea1e",
        "ordinal": 15,
        "field": {
          "Column": {
            "Expression": {
              "SourceRef": {
                "Entity": "Item"
              }
            },
            "Property": "Item Description"
          }
        },
        "type": "Categorical",
        "howCreated": "User"
      },
      {
        "name": "1504ef9f9b225b43e962",
        "ordinal": 16,
        "field": {
          "Column": {
            "Expression": {
              "SourceRef": {
                "Entity": "Item"
              }
            },
            "Property": "Item Inventory Posting Group"
          }
        },
        "type": "Categorical",
        "howCreated": "User"
      },
      {
        "name": "f26a1e25ee6b1455f756",
        "ordinal": 17,
        "field": {
          "Column": {
            "Expression": {
              "SourceRef": {
                "Entity": "Item"
              }
            },
            "Property": "Item No."
          }
        },
        "type": "Categorical",
        "howCreated": "User"
      },
      {
        "name": "2f1b8522c6b5d09a6b87",
        "ordinal": 18,
        "field": {
          "Column": {
            "Expression": {
              "SourceRef": {
                "Entity": "Item"
              }
            },
            "Property": "Item No. & Description"
          }
        },
        "type": "Categorical",
        "howCreated": "User"
      },
      {
        "name": "edd6f6fc8654a902c12a",
        "ordinal": 19,
        "field": {
          "Column": {
            "Expression": {
              "SourceRef": {
                "Entity": "Location"
              }
            },
            "Property": "Location Code"
          }
        },
        "type": "Categorical",
        "howCreated": "User"
      },
      {
        "name": "fad51ca9a557f7adeb47",
        "ordinal": 20,
        "field": {
          "Column": {
            "Expression": {
              "SourceRef": {
                "Entity": "Location"
              }
            },
            "Property": "Location Name"
          }
        },
        "type": "Categorical",
        "howCreated": "User"
      },
      {
        "name": "767559bfce02837b53a5",
        "ordinal": 21,
        "field": {
          "Column": {
            "Expression": {
              "SourceRef": {
                "Entity": "Salesperson"
              }
            },
            "Property": "Salesperson Code"
          }
        },
        "type": "Categorical",
        "howCreated": "User"
      },
      {
        "name": "756be20078136aeb0c65",
        "ordinal": 22,
        "field": {
          "Column": {
            "Expression": {
              "SourceRef": {
                "Entity": "Salesperson"
              }
            },
            "Property": "Salesperson Name"
          }
        },
        "type": "Categorical",
        "howCreated": "User"
      },
      {
        "name": "88e2ecfd38f1d9fa356b",
        "ordinal": 23,
        "field": {
          "Column": {
            "Expression": {
              "SourceRef": {
                "Entity": "Dimension Sets"
              }
            },
            "Property": "Shortcut Dimension 3"
          }
        },
        "type": "Categorical",
        "howCreated": "User"
      },
      {
        "name": "f59ca80123040b15f352",
        "ordinal": 24,
        "field": {
          "Column": {
            "Expression": {
              "SourceRef": {
                "Entity": "Dimension Sets"
              }
            },
            "Property": "Shortcut Dimension 4"
          }
        },
        "type": "Categorical",
        "howCreated": "User"
      },
      {
        "name": "3e65df0bf7dae7e78ac5",
        "ordinal": 25,
        "field": {
          "Column": {
            "Expression": {
              "SourceRef": {
                "Entity": "Dimension Sets"
              }
            },
            "Property": "Shortcut Dimension 5"
          }
        },
        "type": "Categorical",
        "howCreated": "User"
      },
      {
        "name": "c281a008a749f70b76a5",
        "ordinal": 26,
        "field": {
          "Column": {
            "Expression": {
              "SourceRef": {
                "Entity": "Dimension Sets"
              }
            },
            "Property": "Shortcut Dimension 6"
          }
        },
        "type": "Categorical",
        "howCreated": "User"
      },
      {
        "name": "f6b7f9beaa04f8a731bf",
        "ordinal": 27,
        "field": {
          "Column": {
            "Expression": {
              "SourceRef": {
                "Entity": "Dimension Sets"
              }
            },
            "Property": "Shortcut Dimension 7"
          }
        },
        "type": "Categorical",
        "howCreated": "User"
      },
      {
        "name": "1598b8456ed6e08263d2",
        "ordinal": 28,
        "field": {
          "Column": {
            "Expression": {
              "SourceRef": {
                "Entity": "Dimension Sets"
              }
            },
            "Property": "Shortcut Dimension 8"
          }
        },
        "type": "Categorical",
        "howCreated": "User"
      },
      {
        "name": "f9acf72d1a16600e7d04",
        "ordinal": 29,
        "field": {
          "Column": {
            "Expression": {
              "SourceRef": {
                "Entity": "Documents"
              }
            },
            "Property": "Source Table"
          }
        },
        "type": "Categorical",
        "howCreated": "User"
      },
      {
        "name": "55110e3decf3a4c474cf",
        "ordinal": 30,
        "field": {
          "Column": {
            "Expression": {
              "SourceRef": {
                "Entity": "Date"
              }
            },
            "Property": "Fiscal RelativeYearPos"
          }
        },
        "type": "Advanced",
        "howCreated": "User"
      },
      {
        "name": "57d9b105ab2257e9b5aa",
        "ordinal": 31,
        "field": {
          "Column": {
            "Expression": {
              "SourceRef": {
                "Entity": "Type"
              }
            },
            "Property": "Type"
          }
        },
        "type": "Categorical",
        "filter": {
          "Version": 2,
          "From": [
            {
              "Name": "t",
              "Entity": "Type",
              "Type": 0
            }
          ],
          "Where": [
            {
              "Condition": {
                "In": {
                  "Expressions": [
                    {
                      "Column": {
                        "Expression": {
                          "SourceRef": {
                            "Source": "t"
                          }
                        },
                        "Property": "Type"
                      }
                    }
                  ],
                  "Values": [
                    [
                      {
                        "Literal": {
                          "Value": "'Item'"
                        }
                      }
                    ]
                  ]
                }
              }
            }
          ]
        },
        "howCreated": "User",
        "isHiddenInViewMode": true,
        "isLockedInViewMode": true
      }
    ],
    "filterSortOrder": "Custom"
  },
  "pageBinding": {
    "name": "Pod5",
    "type": "Default",
    "parameters": [],
    "acceptsFilterContext": "None"
  }
}