{
  "$schema": "https://developer.microsoft.com/json-schemas/fabric/item/report/definition/visualContainer/2.4.0/schema.json",
  "name": "10b25dc0028b16d50404",
  "position": {
    "x": 25.714285714285715,
    "y": 62.142857142857146,
    "z": 0,
    "height": 632.14285714285722,
    "width": 1227.8571428571429,
    "tabOrder": 0
  },
  "visual": {
    "visualType": "tableEx",
    "query": {
      "queryState": {
        "Values": {
          "projections": [
            {
              "field": {
                "Column": {
                  "Expression": {
                    "SourceRef": {
                      "Entity": "Item Ledger Entries"
                    }
                  },
                  "Property": "Entry No."
                }
              },
              "queryRef": "Item Ledger Entries.ILE Entry No.",
              "nativeQueryRef": "Entry No."
            },
            {
              "field": {
                "Column": {
                  "Expression": {
                    "SourceRef": {
                      "Entity": "Item Ledger Entries"
                    }
                  },
                  "Property": "Entry Type"
                }
              },
              "queryRef": "Item Ledger Entries.Entry Type",
              "nativeQueryRef": "Entry Type"
            },
            {
              "field": {
                "Column": {
                  "Expression": {
                    "SourceRef": {
                      "Entity": "Item Ledger Entries"
                    }
                  },
                  "Property": "Document No."
                }
              },
              "queryRef": "Item Ledger Entries.Document No.",
              "nativeQueryRef": "Document No."
            },
            {
              "field": {
                "Column": {
                  "Expression": {
                    "SourceRef": {
                      "Entity": "Item Ledger Entries"
                    }
                  },
                  "Property": "Document Type"
                }
              },
              "queryRef": "Item Ledger Entries.Document Type",
              "nativeQueryRef": "Document Type"
            },
            {
              "field": {
                "Column": {
                  "Expression": {
                    "SourceRef": {
                      "Entity": "Item"
                    }
                  },
                  "Property": "Item No."
                }
              },
              "queryRef": "Item.Item No.",
              "nativeQueryRef": "Item No."
            },
            {
              "field": {
                "Column": {
                  "Expression": {
                    "SourceRef": {
                      "Entity": "Item"
                    }
                  },
                  "Property": "Item Description"
                }
              },
              "queryRef": "Item.Item Description",
              "nativeQueryRef": "Item Description"
            },
            {
              "field": {
                "Column": {
                  "Expression": {
                    "SourceRef": {
                      "Entity": "Location"
                    }
                  },
                  "Property": "Location Code"
                }
              },
              "queryRef": "Location.Location Code",
              "nativeQueryRef": "Location Code"
            },
            {
              "field": {
                "Measure": {
                  "Expression": {
                    "SourceRef": {
                      "Entity": "Item Ledger Entries"
                    }
                  },
                  "Property": "Quantity"
                }
              },
              "queryRef": "Item Ledger Entries.Quantity",
              "nativeQueryRef": "Quantity (Base)"
            },
            {
              "field": {
                "Measure": {
                  "Expression": {
                    "SourceRef": {
                      "Entity": "Item Ledger Entries"
                    }
                  },
                  "Property": "Remaining Quantity"
                }
              },
              "queryRef": "Item Ledger Entries.Remaining Quantity",
              "nativeQueryRef": "Remaining Quantity (Base)"
            },
            {
              "field": {
                "Measure": {
                  "Expression": {
                    "SourceRef": {
                      "Entity": "Item Ledger Entries"
                    }
                  },
                  "Property": "Invoiced Quantity"
                }
              },
              "queryRef": "Item Ledger Entries.Invoiced Quantity",
              "nativeQueryRef": "Invoiced Quantity (Base)"
            },
            {
              "field": {
                "Column": {
                  "Expression": {
                    "SourceRef": {
                      "Entity": "Date"
                    }
                  },
                  "Property": "Date"
                }
              },
              "queryRef": "Date.Date",
              "nativeQueryRef": "Posting Date",
              "displayName": "Posting Date"
            },
            {
              "field": {
                "Column": {
                  "Expression": {
                    "SourceRef": {
                      "Entity": "Item Ledger Entries"
                    }
                  },
                  "Property": "Unit of Measure Code"
                }
              },
              "queryRef": "Item Ledger Entries.unitOfMeasureCode",
              "nativeQueryRef": "Unit of Measure Code"
            }
          ]
        }
      },
      "sortDefinition": {
        "sort": [
          {
            "field": {
              "Column": {
                "Expression": {
                  "SourceRef": {
                    "Entity": "Item Ledger Entries"
                  }
                },
                "Property": "Entry No."
              }
            },
            "direction": "Ascending"
          }
        ]
      }
    },
    "objects": {
      "values": [
        {
          "properties": {
            "webURL": {
              "expr": {
                "Measure": {
                  "Expression": {
                    "SourceRef": {
                      "Entity": "Item Ledger Entries"
                    }
                  },
                  "Property": "Item Ledger Entries Link"
                }
              }
            }
          },
          "selector": {
            "data": [
              {
                "dataViewWildcard": {
                  "matchingOption": 0
                }
              }
            ],
            "metadata": "Item Ledger Entries.Quantity"
          }
        },
        {
          "properties": {
            "webURL": {
              "expr": {
                "Measure": {
                  "Expression": {
                    "SourceRef": {
                      "Entity": "Item Ledger Entries"
                    }
                  },
                  "Property": "Item Ledger Entries Link"
                }
              }
            }
          },
          "selector": {
            "data": [
              {
                "dataViewWildcard": {
                  "matchingOption": 0
                }
              }
            ],
            "metadata": "Item Ledger Entries.Remaining Quantity"
          }
        },
        {
          "properties": {
            "webURL": {
              "expr": {
                "Measure": {
                  "Expression": {
                    "SourceRef": {
                      "Entity": "Item Ledger Entries"
                    }
                  },
                  "Property": "Item Ledger Entries Link"
                }
              }
            }
          },
          "selector": {
            "data": [
              {
                "dataViewWildcard": {
                  "matchingOption": 0
                }
              }
            ],
            "metadata": "Item Ledger Entries.Invoiced Quantity"
          }
        }
      ]
    },
    "visualContainerObjects": {
      "title": [
        {
          "properties": {
            "text": {
              "expr": {
                "Measure": {
                  "Expression": {
                    "SourceRef": {
                      "Entity": "Translated Localized Labels"
                    }
                  },
                  "Property": "Item Ledger Entry Drill through Label"
                }
              }
            }
          }
        }
      ]
    }
  }
}