{
  "$schema": "https://developer.microsoft.com/json-schemas/fabric/item/report/definition/page/2.0.0/schema.json",
  "name": "ReportSection1636f46ab3cad0c163a4",
  "displayName": "Customer Ledger Entries Drill Through",
  "displayOption": "FitToPage",
  "height": 720,
  "width": 1280,
  "filterConfig": {
    "filters": [
      {
        "name": "Filter313b08e087c40a9595d7",
        "field": {
          "Column": {
            "Expression": {
              "SourceRef": {
                "Entity": "Customer Ledger Entries"
              }
            },
            "Property": "Document No."
          }
        },
        "type": "Categorical",
        "filter": {
          "Version": 2,
          "From": [
            {
              "Name": "c",
              "Entity": "Customer Ledger Entries",
              "Type": 0
            }
          ],
          "Where": [
            {
              "Condition": {
                "In": {
                  "Expressions": [
                    {
                      "Column": {
                        "Expression": {
                          "SourceRef": {
                            "Source": "c"
                          }
                        },
                        "Property": "Document No."
                      }
                    }
                  ],
                  "Values": [
                    [
                      {
                        "Literal": {
                          "Value": "'G04002'"
                        }
                      }
                    ]
                  ]
                }
              }
            }
          ]
        },
        "howCreated": "Drillthrough"
      },
      {
        "name": "Filter5f2f9b7a6209e21bc267",
        "field": {
          "Column": {
            "Expression": {
              "SourceRef": {
                "Entity": "Customers"
              }
            },
            "Property": "Customer No. & Name"
          }
        },
        "type": "Categorical",
        "howCreated": "Drillthrough"
      },
      {
        "name": "Filter28ef2114cd51d83c4e35",
        "field": {
          "Column": {
            "Expression": {
              "SourceRef": {
                "Entity": "Customers"
              }
            },
            "Property": "Customer Name"
          }
        },
        "type": "Categorical",
        "filter": {
          "Version": 2,
          "From": [
            {
              "Name": "c",
              "Entity": "Customers",
              "Type": 0
            }
          ],
          "Where": [
            {
              "Condition": {
                "In": {
                  "Expressions": [
                    {
                      "Column": {
                        "Expression": {
                          "SourceRef": {
                            "Source": "c"
                          }
                        },
                        "Property": "Customer Name"
                      }
                    }
                  ],
                  "Values": [
                    [
                      {
                        "Literal": {
                          "Value": "'Adatum Corporation'"
                        }
                      }
                    ]
                  ]
                }
              }
            }
          ]
        },
        "howCreated": "Drillthrough"
      },
      {
        "name": "Filterd5b005d5577b9f83bf81",
        "field": {
          "Column": {
            "Expression": {
              "SourceRef": {
                "Entity": "Customers"
              }
            },
            "Property": "Customer No."
          }
        },
        "type": "Categorical",
        "howCreated": "Drillthrough"
      }
    ]
  },
  "pageBinding": {
    "name": "Pod19",
    "type": "Drillthrough",
    "parameters": [
      {
        "name": "Param_Filter313b08e087c40a9595d7",
        "boundFilter": "Filter313b08e087c40a9595d7",
        "fieldExpr": {
          "Column": {
            "Expression": {
              "SourceRef": {
                "Entity": "Customer Ledger Entries"
              }
            },
            "Property": "Document No."
          }
        }
      },
      {
        "name": "Param_Filter5f2f9b7a6209e21bc267",
        "boundFilter": "Filter5f2f9b7a6209e21bc267",
        "fieldExpr": {
          "Column": {
            "Expression": {
              "SourceRef": {
                "Entity": "Customers"
              }
            },
            "Property": "Customer No. & Name"
          }
        }
      },
      {
        "name": "Param_Filter28ef2114cd51d83c4e35",
        "boundFilter": "Filter28ef2114cd51d83c4e35",
        "fieldExpr": {
          "Column": {
            "Expression": {
              "SourceRef": {
                "Entity": "Customers"
              }
            },
            "Property": "Customer Name"
          }
        }
      },
      {
        "name": "Param_Filterd5b005d5577b9f83bf81",
        "boundFilter": "Filterd5b005d5577b9f83bf81",
        "fieldExpr": {
          "Column": {
            "Expression": {
              "SourceRef": {
                "Entity": "Customers"
              }
            },
            "Property": "Customer No."
          }
        }
      }
    ]
  },
  "visibility": "HiddenInViewMode"
}